{
  "country": "us",
  "fetchedAt": "2025-10-09T03:44:18.605Z",
  "keywords": [
    {
      "keyword": "Mono- and diacetyltartaric acid esters of mono- and diglycerides of fatty acids",
      "metrics": []
    },
    {
      "keyword": "E472E",
      "metrics": []
    },
    {
      "keyword": "Mono- and diacetyl tartaric acid esters of mono- and diglycerides of fatty acids",
      "metrics": []
    },
    {
      "keyword": "DATEM",
      "metrics": [
        {
          "date": "2016-01-01T00:00:00Z",
          "volume": 5912
        },
        {
          "date": "2016-02-01T00:00:00Z",
          "volume": 5212
        },
        {
          "date": "2016-03-01T00:00:00Z",
          "volume": 4244
        },
        {
          "date": "2016-04-01T00:00:00Z",
          "volume": 4546
        },
        {
          "date": "2016-05-01T00:00:00Z",
          "volume": 4351
        },
        {
          "date": "2016-06-01T00:00:00Z",
          "volume": 5455
        },
        {
          "date": "2016-07-01T00:00:00Z",
          "volume": 4516
        },
        {
          "date": "2016-08-01T00:00:00Z",
          "volume": 4176
        },
        {
          "date": "2016-09-01T00:00:00Z",
          "volume": 3973
        },
        {
          "date": "2016-10-01T00:00:00Z",
          "volume": 4188
        },
        {
          "date": "2016-11-01T00:00:00Z",
          "volume": 4027
        },
        {
          "date": "2016-12-01T00:00:00Z",
          "volume": 3284
        },
        {
          "date": "2017-01-01T00:00:00Z",
          "volume": 4922
        },
        {
          "date": "2017-02-01T00:00:00Z",
          "volume": 4908
        },
        {
          "date": "2017-03-01T00:00:00Z",
          "volume": 5237
        },
        {
          "date": "2017-04-01T00:00:00Z",
          "volume": 4249
        },
        {
          "date": "2017-05-01T00:00:00Z",
          "volume": 4732
        },
        {
          "date": "2017-06-01T00:00:00Z",
          "volume": 4123
        },
        {
          "date": "2017-07-01T00:00:00Z",
          "volume": 4333
        },
        {
          "date": "2017-08-01T00:00:00Z",
          "volume": 4558
        },
        {
          "date": "2017-09-01T00:00:00Z",
          "volume": 4366
        },
        {
          "date": "2017-10-01T00:00:00Z",
          "volume": 4815
        },
        {
          "date": "2017-11-01T00:00:00Z",
          "volume": 3894
        },
        {
          "date": "2017-12-01T00:00:00Z",
          "volume": 4506
        },
        {
          "date": "2018-01-01T00:00:00Z",
          "volume": 5178
        },
        {
          "date": "2018-02-01T00:00:00Z",
          "volume": 6013
        },
        {
          "date": "2018-03-01T00:00:00Z",
          "volume": 5444
        },
        {
          "date": "2018-04-01T00:00:00Z",
          "volume": 5212
        },
        {
          "date": "2018-05-01T00:00:00Z",
          "volume": 4211
        },
        {
          "date": "2018-06-01T00:00:00Z",
          "volume": 3945
        },
        {
          "date": "2018-07-01T00:00:00Z",
          "volume": 4424
        },
        {
          "date": "2018-08-01T00:00:00Z",
          "volume": 5023
        },
        {
          "date": "2018-09-01T00:00:00Z",
          "volume": 3889
        },
        {
          "date": "2018-10-01T00:00:00Z",
          "volume": 4995
        },
        {
          "date": "2018-11-01T00:00:00Z",
          "volume": 5155
        },
        {
          "date": "2018-12-01T00:00:00Z",
          "volume": 3983
        },
        {
          "date": "2019-01-01T00:00:00Z",
          "volume": 5794
        },
        {
          "date": "2019-02-01T00:00:00Z",
          "volume": 4834
        },
        {
          "date": "2019-03-01T00:00:00Z",
          "volume": 4938
        },
        {
          "date": "2019-04-01T00:00:00Z",
          "volume": 4061
        },
        {
          "date": "2019-05-01T00:00:00Z",
          "volume": 4303
        },
        {
          "date": "2019-06-01T00:00:00Z",
          "volume": 4250
        },
        {
          "date": "2019-07-01T00:00:00Z",
          "volume": 4708
        },
        {
          "date": "2019-08-01T00:00:00Z",
          "volume": 4843
        },
        {
          "date": "2019-09-01T00:00:00Z",
          "volume": 4564
        },
        {
          "date": "2019-10-01T00:00:00Z",
          "volume": 3895
        },
        {
          "date": "2019-11-01T00:00:00Z",
          "volume": 3889
        },
        {
          "date": "2019-12-01T00:00:00Z",
          "volume": 3271
        },
        {
          "date": "2020-01-01T00:00:00Z",
          "volume": 3950
        },
        {
          "date": "2020-02-01T00:00:00Z",
          "volume": 3396
        },
        {
          "date": "2020-03-01T00:00:00Z",
          "volume": 2891
        },
        {
          "date": "2020-04-01T00:00:00Z",
          "volume": 3397
        },
        {
          "date": "2020-05-01T00:00:00Z",
          "volume": 2533
        },
        {
          "date": "2020-06-01T00:00:00Z",
          "volume": 3159
        },
        {
          "date": "2020-07-01T00:00:00Z",
          "volume": 2551
        },
        {
          "date": "2020-08-01T00:00:00Z",
          "volume": 2634
        },
        {
          "date": "2020-09-01T00:00:00Z",
          "volume": 2533
        },
        {
          "date": "2020-10-01T00:00:00Z",
          "volume": 3091
        },
        {
          "date": "2020-11-01T00:00:00Z",
          "volume": 2249
        },
        {
          "date": "2020-12-01T00:00:00Z",
          "volume": 3395
        },
        {
          "date": "2021-01-01T00:00:00Z",
          "volume": 4154
        },
        {
          "date": "2021-02-01T00:00:00Z",
          "volume": 2597
        },
        {
          "date": "2021-03-01T00:00:00Z",
          "volume": 3269
        },
        {
          "date": "2021-04-01T00:00:00Z",
          "volume": 2589
        },
        {
          "date": "2021-05-01T00:00:00Z",
          "volume": 2546
        },
        {
          "date": "2021-06-01T00:00:00Z",
          "volume": 3355
        },
        {
          "date": "2021-07-01T00:00:00Z",
          "volume": 2704
        },
        {
          "date": "2021-08-01T00:00:00Z",
          "volume": 3153
        },
        {
          "date": "2021-09-01T00:00:00Z",
          "volume": 3346
        },
        {
          "date": "2021-10-01T00:00:00Z",
          "volume": 3570
        },
        {
          "date": "2021-11-01T00:00:00Z",
          "volume": 2291
        },
        {
          "date": "2021-12-01T00:00:00Z",
          "volume": 3373
        },
        {
          "date": "2022-01-01T00:00:00Z",
          "volume": 3861
        },
        {
          "date": "2022-02-01T00:00:00Z",
          "volume": 3337
        },
        {
          "date": "2022-03-01T00:00:00Z",
          "volume": 3112
        },
        {
          "date": "2022-04-01T00:00:00Z",
          "volume": 2976
        },
        {
          "date": "2022-05-01T00:00:00Z",
          "volume": 3451
        },
        {
          "date": "2022-06-01T00:00:00Z",
          "volume": 2845
        },
        {
          "date": "2022-07-01T00:00:00Z",
          "volume": 3219
        },
        {
          "date": "2022-08-01T00:00:00Z",
          "volume": 3400
        },
        {
          "date": "2022-09-01T00:00:00Z",
          "volume": 3003
        },
        {
          "date": "2022-10-01T00:00:00Z",
          "volume": 2951
        },
        {
          "date": "2022-11-01T00:00:00Z",
          "volume": 2853
        },
        {
          "date": "2022-12-01T00:00:00Z",
          "volume": 2336
        },
        {
          "date": "2023-01-01T00:00:00Z",
          "volume": 4497
        },
        {
          "date": "2023-02-01T00:00:00Z",
          "volume": 3769
        },
        {
          "date": "2023-03-01T00:00:00Z",
          "volume": 3422
        },
        {
          "date": "2023-04-01T00:00:00Z",
          "volume": 3453
        },
        {
          "date": "2023-05-01T00:00:00Z",
          "volume": 3617
        },
        {
          "date": "2023-06-01T00:00:00Z",
          "volume": 3456
        },
        {
          "date": "2023-07-01T00:00:00Z",
          "volume": 3768
        },
        {
          "date": "2023-08-01T00:00:00Z",
          "volume": 4013
        },
        {
          "date": "2023-09-01T00:00:00Z",
          "volume": 4143
        },
        {
          "date": "2023-10-01T00:00:00Z",
          "volume": 4854
        },
        {
          "date": "2023-11-01T00:00:00Z",
          "volume": 4140
        },
        {
          "date": "2023-12-01T00:00:00Z",
          "volume": 2626
        },
        {
          "date": "2024-01-01T00:00:00Z",
          "volume": 4442
        },
        {
          "date": "2024-02-01T00:00:00Z",
          "volume": 3860
        },
        {
          "date": "2024-03-01T00:00:00Z",
          "volume": 3719
        },
        {
          "date": "2024-04-01T00:00:00Z",
          "volume": 3467
        },
        {
          "date": "2024-05-01T00:00:00Z",
          "volume": 3378
        },
        {
          "date": "2024-06-01T00:00:00Z",
          "volume": 3471
        },
        {
          "date": "2024-07-01T00:00:00Z",
          "volume": 3505
        },
        {
          "date": "2024-08-01T00:00:00Z",
          "volume": 3629
        },
        {
          "date": "2024-09-01T00:00:00Z",
          "volume": 3532
        },
        {
          "date": "2024-10-01T00:00:00Z",
          "volume": 3801
        },
        {
          "date": "2024-11-01T00:00:00Z",
          "volume": 3388
        },
        {
          "date": "2024-12-01T00:00:00Z",
          "volume": 3206
        },
        {
          "date": "2025-01-01T00:00:00Z",
          "volume": 4307
        },
        {
          "date": "2025-02-01T00:00:00Z",
          "volume": 3810
        },
        {
          "date": "2025-03-01T00:00:00Z",
          "volume": 3671
        },
        {
          "date": "2025-04-01T00:00:00Z",
          "volume": 3423
        },
        {
          "date": "2025-05-01T00:00:00Z",
          "volume": 3334
        },
        {
          "date": "2025-06-01T00:00:00Z",
          "volume": 3426
        },
        {
          "date": "2025-07-01T00:00:00Z",
          "volume": 3459
        },
        {
          "date": "2025-08-01T00:00:00Z",
          "volume": 3582
        },
        {
          "date": "2025-09-01T00:00:00Z",
          "volume": 3487
        },
        {
          "date": "2025-10-01T00:00:00Z",
          "volume": 3752
        },
        {
          "date": "2025-11-01T00:00:00Z",
          "volume": 3344
        },
        {
          "date": "2025-12-01T00:00:00Z",
          "volume": 3164
        }
      ]
    },
    {
      "keyword": "Mono- and diacetyltartaric esters of mono- and diglycerides of fatty acids",
      "metrics": []
    },
    {
      "keyword": "emulsifier E472e",
      "metrics": []
    }
  ]
}
