{
  "updatedAt": "2025-10-12T02:33:40.928Z",
  "answers": [
    {
      "q": "is gellan gum bad for you",
      "a": "No—it's considered safe by major regulators (GRAS in the U.S., approved in the EU); very high intakes may cause gas or loose stools, but typical food amounts are well tolerated.",
      "answeredAt": "2025-10-12T02:33:40.928Z"
    },
    {
      "q": "what is gellan gum made of",
      "a": "It's a polysaccharide produced by fermenting sugars with the bacterium Sphingomonas elodea; chemically it contains repeating units of glucose, glucuronic acid, and rhamnose.",
      "answeredAt": "2025-10-12T02:33:40.928Z"
    },
    {
      "q": "is gellan gum vegan",
      "a": "Yes—it's made by microbial fermentation and is not animal-derived, so it's generally considered vegan.",
      "answeredAt": "2025-10-12T02:33:40.928Z"
    },
    {
      "q": "is gellan gum bad for your gut",
      "a": "Generally no; it's not digested and is used in small amounts, though large amounts can cause bloating or laxative effects in some people, with no evidence of gut-lining harm at permitted levels.",
      "answeredAt": "2025-10-12T02:33:40.928Z"
    },
    {
      "q": "is gellan gum inflammatory",
      "a": "No; there's no evidence it promotes inflammation at approved food-use levels, and regulatory evaluations have not identified pro-inflammatory effects.",
      "answeredAt": "2025-10-12T02:33:40.928Z"
    }
  ]
}
