{
  "keywords": [
    "Orange GGN",
    "E111",
    "Alpha-naphthol",
    "Alpha-naphtol",
    "alpha-naphthol orange"
  ],
  "country": "us",
  "fetchedAt": "2025-10-09T03:25:43.312Z",
  "questions": [
    {
      "keyword": "how long does e111 pill last",
      "volume": 40,
      "original_keyword": "E111",
      "parent_topic": "how long does adderall last",
      "intents": [
        "informational",
        "branded"
      ]
    },
    {
      "keyword": "e111 card how long does it take",
      "volume": 10,
      "original_keyword": "E111",
      "parent_topic": "",
      "intents": []
    },
    {
      "keyword": "e111 what does it cover you for",
      "volume": 10,
      "original_keyword": "E111",
      "parent_topic": "",
      "intents": []
    },
    {
      "keyword": "how to claim on e111",
      "volume": 10,
      "original_keyword": "E111",
      "parent_topic": "",
      "intents": []
    },
    {
      "keyword": "how to separate lauric acid from alpha naphthol",
      "volume": 10,
      "original_keyword": "Alpha-naphthol",
      "parent_topic": "",
      "intents": []
    },
    {
      "keyword": "what does an e111 cover you for",
      "volume": 10,
      "original_keyword": "E111",
      "parent_topic": "",
      "intents": []
    },
    {
      "keyword": "what does e111 cover in spain",
      "volume": 10,
      "original_keyword": "E111",
      "parent_topic": "",
      "intents": []
    },
    {
      "keyword": "what does the e111 cover you for",
      "volume": 10,
      "original_keyword": "E111",
      "parent_topic": "",
      "intents": []
    },
    {
      "keyword": "what is the e111 form",
      "volume": 10,
      "original_keyword": "E111",
      "parent_topic": "",
      "intents": []
    },
    {
      "keyword": "where do i get an e111 card",
      "volume": 10,
      "original_keyword": "E111",
      "parent_topic": "",
      "intents": []
    }
  ]
}
