{
  "keyword": "Citrus Red 2",
  "country": "us",
  "fetchedAt": "2025-10-06T04:18:44.763Z",
  "questions": [
    {
      "keyword": "what foods have citrus red 2",
      "volume": 10,
      "parent_topic": "",
      "intents": []
    },
    {
      "keyword": "what is citrus red 2",
      "volume": 10,
      "parent_topic": "",
      "intents": []
    },
    {
      "keyword": "how is citrus red #2 applied to oranges",
      "volume": 0,
      "parent_topic": "",
      "intents": []
    },
    {
      "keyword": "how many prodtcs have citrus red no. 2",
      "volume": 0,
      "parent_topic": "",
      "intents": []
    },
    {
      "keyword": "what is a structural element common to all certified color additives except citrus red no. 2",
      "volume": 0,
      "parent_topic": "",
      "intents": []
    },
    {
      "keyword": "what is citrus red 2 used for",
      "volume": 0,
      "parent_topic": "",
      "intents": []
    },
    {
      "keyword": "what is citrus red no. 2",
      "volume": 0,
      "parent_topic": "",
      "intents": []
    },
    {
      "keyword": "what is citrus red no. 2 allergy",
      "volume": 0,
      "parent_topic": "",
      "intents": []
    },
    {
      "keyword": "which oranges have citrus red 2",
      "volume": 0,
      "parent_topic": "",
      "intents": []
    }
  ]
}
