{
  "updatedAt": "2025-10-12T02:42:51.725Z",
  "answers": [
    {
      "q": "what is a dangerously low oxygen level",
      "a": "An oxygen saturation (SpO2) below 90% is generally considered dangerously low and warrants urgent evaluation; on arterial blood gas, a PaO2 below about 60 mmHg indicates hypoxemia.",
      "answeredAt": "2025-10-12T02:42:51.725Z"
    },
    {
      "q": "how many valence electrons does oxygen have",
      "a": "Oxygen has six valence electrons.",
      "answeredAt": "2025-10-12T02:42:51.725Z"
    },
    {
      "q": "how to increase blood oxygen level",
      "a": "Move to fresh, well-ventilated air, sit upright, and practice slow deep breathing; avoid smoking and address underlying lung or heart conditions. If levels remain low, seek medical care—supplemental oxygen should only be used as prescribed.",
      "answeredAt": "2025-10-12T02:42:51.725Z"
    },
    {
      "q": "how many electrons does oxygen have",
      "a": "A neutral oxygen atom has 8 electrons.",
      "answeredAt": "2025-10-12T02:42:51.725Z"
    },
    {
      "q": "how much oxygen is in the air",
      "a": "Dry air is about 20.9% oxygen by volume (roughly 21%).",
      "answeredAt": "2025-10-12T02:42:51.725Z"
    }
  ]
}
