{
  "country": "us",
  "fetchedAt": "2025-10-09T03:44:19.910Z",
  "metrics": [
    {
      "date": "2016-01-01T00:00:00Z",
      "volume": 1850
    },
    {
      "date": "2016-02-01T00:00:00Z",
      "volume": 2681
    },
    {
      "date": "2016-03-01T00:00:00Z",
      "volume": 2194
    },
    {
      "date": "2016-04-01T00:00:00Z",
      "volume": 2578
    },
    {
      "date": "2016-05-01T00:00:00Z",
      "volume": 3357
    },
    {
      "date": "2016-06-01T00:00:00Z",
      "volume": 2904
    },
    {
      "date": "2016-07-01T00:00:00Z",
      "volume": 1612
    },
    {
      "date": "2016-08-01T00:00:00Z",
      "volume": 3327
    },
    {
      "date": "2016-09-01T00:00:00Z",
      "volume": 1434
    },
    {
      "date": "2016-10-01T00:00:00Z",
      "volume": 2751
    },
    {
      "date": "2016-11-01T00:00:00Z",
      "volume": 1586
    },
    {
      "date": "2016-12-01T00:00:00Z",
      "volume": 2502
    },
    {
      "date": "2017-01-01T00:00:00Z",
      "volume": 2567
    },
    {
      "date": "2017-02-01T00:00:00Z",
      "volume": 2243
    },
    {
      "date": "2017-03-01T00:00:00Z",
      "volume": 3059
    },
    {
      "date": "2017-04-01T00:00:00Z",
      "volume": 2004
    },
    {
      "date": "2017-05-01T00:00:00Z",
      "volume": 2464
    },
    {
      "date": "2017-06-01T00:00:00Z",
      "volume": 2076
    },
    {
      "date": "2017-07-01T00:00:00Z",
      "volume": 1246
    },
    {
      "date": "2017-08-01T00:00:00Z",
      "volume": 2252
    },
    {
      "date": "2017-09-01T00:00:00Z",
      "volume": 2811
    },
    {
      "date": "2017-10-01T00:00:00Z",
      "volume": 2080
    },
    {
      "date": "2017-11-01T00:00:00Z",
      "volume": 1362
    },
    {
      "date": "2017-12-01T00:00:00Z",
      "volume": 1413
    },
    {
      "date": "2018-01-01T00:00:00Z",
      "volume": 2181
    },
    {
      "date": "2018-02-01T00:00:00Z",
      "volume": 2122
    },
    {
      "date": "2018-03-01T00:00:00Z",
      "volume": 2770
    },
    {
      "date": "2018-04-01T00:00:00Z",
      "volume": 2210
    },
    {
      "date": "2018-05-01T00:00:00Z",
      "volume": 2166
    },
    {
      "date": "2018-06-01T00:00:00Z",
      "volume": 2422
    },
    {
      "date": "2018-07-01T00:00:00Z",
      "volume": 1690
    },
    {
      "date": "2018-08-01T00:00:00Z",
      "volume": 2201
    },
    {
      "date": "2018-09-01T00:00:00Z",
      "volume": 2572
    },
    {
      "date": "2018-10-01T00:00:00Z",
      "volume": 3739
    },
    {
      "date": "2018-11-01T00:00:00Z",
      "volume": 2157
    },
    {
      "date": "2018-12-01T00:00:00Z",
      "volume": 1980
    },
    {
      "date": "2019-01-01T00:00:00Z",
      "volume": 2363
    },
    {
      "date": "2019-02-01T00:00:00Z",
      "volume": 2357
    },
    {
      "date": "2019-03-01T00:00:00Z",
      "volume": 2591
    },
    {
      "date": "2019-04-01T00:00:00Z",
      "volume": 2149
    },
    {
      "date": "2019-05-01T00:00:00Z",
      "volume": 1829
    },
    {
      "date": "2019-06-01T00:00:00Z",
      "volume": 1877
    },
    {
      "date": "2019-07-01T00:00:00Z",
      "volume": 1515
    },
    {
      "date": "2019-08-01T00:00:00Z",
      "volume": 2301
    },
    {
      "date": "2019-09-01T00:00:00Z",
      "volume": 1680
    },
    {
      "date": "2019-10-01T00:00:00Z",
      "volume": 1552
    },
    {
      "date": "2019-11-01T00:00:00Z",
      "volume": 1362
    },
    {
      "date": "2019-12-01T00:00:00Z",
      "volume": 1234
    },
    {
      "date": "2020-01-01T00:00:00Z",
      "volume": 863
    },
    {
      "date": "2020-02-01T00:00:00Z",
      "volume": 1577
    },
    {
      "date": "2020-03-01T00:00:00Z",
      "volume": 1395
    },
    {
      "date": "2020-04-01T00:00:00Z",
      "volume": 668
    },
    {
      "date": "2020-05-01T00:00:00Z",
      "volume": 241
    },
    {
      "date": "2020-06-01T00:00:00Z",
      "volume": 841
    },
    {
      "date": "2020-07-01T00:00:00Z",
      "volume": 780
    },
    {
      "date": "2020-08-01T00:00:00Z",
      "volume": 621
    },
    {
      "date": "2020-09-01T00:00:00Z",
      "volume": 910
    },
    {
      "date": "2020-10-01T00:00:00Z",
      "volume": 1103
    },
    {
      "date": "2020-11-01T00:00:00Z",
      "volume": 659
    },
    {
      "date": "2020-12-01T00:00:00Z",
      "volume": 182
    },
    {
      "date": "2021-01-01T00:00:00Z",
      "volume": 665
    },
    {
      "date": "2021-02-01T00:00:00Z",
      "volume": 1148
    },
    {
      "date": "2021-03-01T00:00:00Z",
      "volume": 1029
    },
    {
      "date": "2021-04-01T00:00:00Z",
      "volume": 813
    },
    {
      "date": "2021-05-01T00:00:00Z",
      "volume": 866
    },
    {
      "date": "2021-06-01T00:00:00Z",
      "volume": 704
    },
    {
      "date": "2021-07-01T00:00:00Z",
      "volume": 1564
    },
    {
      "date": "2021-08-01T00:00:00Z",
      "volume": 2219
    },
    {
      "date": "2021-09-01T00:00:00Z",
      "volume": 1026
    },
    {
      "date": "2021-10-01T00:00:00Z",
      "volume": 2012
    },
    {
      "date": "2021-11-01T00:00:00Z",
      "volume": 1117
    },
    {
      "date": "2021-12-01T00:00:00Z",
      "volume": 793
    },
    {
      "date": "2022-01-01T00:00:00Z",
      "volume": 1433
    },
    {
      "date": "2022-02-01T00:00:00Z",
      "volume": 1175
    },
    {
      "date": "2022-03-01T00:00:00Z",
      "volume": 1101
    },
    {
      "date": "2022-04-01T00:00:00Z",
      "volume": 849
    },
    {
      "date": "2022-05-01T00:00:00Z",
      "volume": 821
    },
    {
      "date": "2022-06-01T00:00:00Z",
      "volume": 813
    },
    {
      "date": "2022-07-01T00:00:00Z",
      "volume": 672
    },
    {
      "date": "2022-08-01T00:00:00Z",
      "volume": 956
    },
    {
      "date": "2022-09-01T00:00:00Z",
      "volume": 806
    },
    {
      "date": "2022-10-01T00:00:00Z",
      "volume": 854
    },
    {
      "date": "2022-11-01T00:00:00Z",
      "volume": 1026
    },
    {
      "date": "2022-12-01T00:00:00Z",
      "volume": 1450
    },
    {
      "date": "2023-01-01T00:00:00Z",
      "volume": 1869
    },
    {
      "date": "2023-02-01T00:00:00Z",
      "volume": 1955
    },
    {
      "date": "2023-03-01T00:00:00Z",
      "volume": 1478
    },
    {
      "date": "2023-04-01T00:00:00Z",
      "volume": 1314
    },
    {
      "date": "2023-05-01T00:00:00Z",
      "volume": 1125
    },
    {
      "date": "2023-06-01T00:00:00Z",
      "volume": 2042
    },
    {
      "date": "2023-07-01T00:00:00Z",
      "volume": 1682
    },
    {
      "date": "2023-08-01T00:00:00Z",
      "volume": 829
    },
    {
      "date": "2023-09-01T00:00:00Z",
      "volume": 1728
    },
    {
      "date": "2023-10-01T00:00:00Z",
      "volume": 727
    },
    {
      "date": "2023-11-01T00:00:00Z",
      "volume": 1372
    },
    {
      "date": "2023-12-01T00:00:00Z",
      "volume": 647
    },
    {
      "date": "2024-01-01T00:00:00Z",
      "volume": 896
    },
    {
      "date": "2024-02-01T00:00:00Z",
      "volume": 1210
    },
    {
      "date": "2024-03-01T00:00:00Z",
      "volume": 1215
    },
    {
      "date": "2024-04-01T00:00:00Z",
      "volume": 1106
    },
    {
      "date": "2024-05-01T00:00:00Z",
      "volume": 1077
    },
    {
      "date": "2024-06-01T00:00:00Z",
      "volume": 1182
    },
    {
      "date": "2024-07-01T00:00:00Z",
      "volume": 1018
    },
    {
      "date": "2024-08-01T00:00:00Z",
      "volume": 1233
    },
    {
      "date": "2024-09-01T00:00:00Z",
      "volume": 1226
    },
    {
      "date": "2024-10-01T00:00:00Z",
      "volume": 1320
    },
    {
      "date": "2024-11-01T00:00:00Z",
      "volume": 915
    },
    {
      "date": "2024-12-01T00:00:00Z",
      "volume": 924
    },
    {
      "date": "2025-01-01T00:00:00Z",
      "volume": 1099
    },
    {
      "date": "2025-02-01T00:00:00Z",
      "volume": 1141
    },
    {
      "date": "2025-03-01T00:00:00Z",
      "volume": 1151
    },
    {
      "date": "2025-04-01T00:00:00Z",
      "volume": 951
    },
    {
      "date": "2025-05-01T00:00:00Z",
      "volume": 1000
    },
    {
      "date": "2025-06-01T00:00:00Z",
      "volume": 1083
    },
    {
      "date": "2025-07-01T00:00:00Z",
      "volume": 929
    },
    {
      "date": "2025-08-01T00:00:00Z",
      "volume": 1175
    },
    {
      "date": "2025-09-01T00:00:00Z",
      "volume": 1161
    },
    {
      "date": "2025-10-01T00:00:00Z",
      "volume": 1273
    },
    {
      "date": "2025-11-01T00:00:00Z",
      "volume": 877
    },
    {
      "date": "2025-12-01T00:00:00Z",
      "volume": 880
    }
  ],
  "sparkline": [
    2398,
    2131,
    2351,
    1901,
    820,
    1163,
    996,
    1397,
    1110,
    1060
  ]
}
