{
  "keywords": [
    "Potassium sodium tartrate",
    "E337"
  ],
  "country": "us",
  "fetchedAt": "2025-10-09T03:27:56.531Z",
  "questions": [
    {
      "keyword": "e337 sodium potassium tartrate is in what foods",
      "volume": 0,
      "original_keyword": "Potassium sodium tartrate",
      "parent_topic": "",
      "intents": []
    },
    {
      "keyword": "how to grow potassium sodium tartrate crystal",
      "volume": 0,
      "original_keyword": "Potassium sodium tartrate",
      "parent_topic": "",
      "intents": []
    },
    {
      "keyword": "how to prepare potassium sodium tartrate",
      "volume": 0,
      "original_keyword": "Potassium sodium tartrate",
      "parent_topic": "",
      "intents": []
    },
    {
      "keyword": "how to prepare potassium sodium tartrate solution from sodium and potasium tartarate",
      "volume": 0,
      "original_keyword": "Potassium sodium tartrate",
      "parent_topic": "",
      "intents": []
    },
    {
      "keyword": "how to prepare potassium sodium tartrate solution from sodium and potassium tartrate",
      "volume": 0,
      "original_keyword": "Potassium sodium tartrate",
      "parent_topic": "",
      "intents": []
    },
    {
      "keyword": "potassium sodium tartrate is in what foods",
      "volume": 0,
      "original_keyword": "Potassium sodium tartrate",
      "parent_topic": "",
      "intents": []
    },
    {
      "keyword": "potassium sodium tartrate where to buy",
      "volume": 0,
      "original_keyword": "Potassium sodium tartrate",
      "parent_topic": "",
      "intents": []
    },
    {
      "keyword": "sodium potassium tartrate is in what foods",
      "volume": 0,
      "original_keyword": "Potassium sodium tartrate",
      "parent_topic": "",
      "intents": []
    },
    {
      "keyword": "what food is e337 sodium potassium tartrate in",
      "volume": 0,
      "original_keyword": "Potassium sodium tartrate",
      "parent_topic": "",
      "intents": []
    },
    {
      "keyword": "what is potassium sodium tartrate",
      "volume": 0,
      "original_keyword": "Potassium sodium tartrate",
      "parent_topic": "",
      "intents": []
    }
  ]
}
