{
  "updatedAt": "2025-10-12T02:37:23.912Z",
  "answers": [
    {
      "q": "how much oil in 2001 ford e350i take",
      "a": "That’s a vehicle question; E350(i) refers to sodium malate, a food additive, and is unrelated to engine oil capacities.",
      "answeredAt": "2025-10-12T02:37:23.912Z"
    },
    {
      "q": "what is sodium hydrogen malate used for?",
      "a": "Sodium hydrogen malate (E350(ii)) is used as an acidity regulator and buffer that provides mild tartness and helps stabilize pH in foods like beverages, jams, and confectionery.",
      "answeredAt": "2025-10-12T02:37:23.912Z"
    },
    {
      "q": "what is sodium malate sodium level",
      "a": "Disodium malate (E350(i)) is about 26% sodium by weight (~260 mg sodium per gram), while monosodium malate (E350(ii)) is about 15% (~150 mg/g).",
      "answeredAt": "2025-10-12T02:37:23.912Z"
    },
    {
      "q": "what is sodium malate used for in foods",
      "a": "It functions mainly as an acidity regulator/buffering agent and humectant, adding gentle tartness, controlling pH, and helping retain moisture in products like beverages, confectionery, and baked goods.",
      "answeredAt": "2025-10-12T02:37:23.912Z"
    },
    {
      "q": "why add sodium malate in salmon caviar",
      "a": "To gently regulate pH and act as a humectant, which helps stabilize texture, reduce drip, and subtly enhance flavor/salt perception for better shelf-life.",
      "answeredAt": "2025-10-12T02:37:23.912Z"
    }
  ]
}
